ovos_skill_moviemaster/LICENSE
ovos_skill_moviemaster/MANIFEST.in
ovos_skill_moviemaster/PrimaryLogo_Green.png
ovos_skill_moviemaster/README.md
ovos_skill_moviemaster/__init__.py
ovos_skill_moviemaster/requirements.txt
ovos_skill_moviemaster/supported_py_versions.json
ovos_skill_moviemaster/version.py
ovos_skill_moviemaster/locale/ca-es/skill.json
ovos_skill_moviemaster/locale/ca-es/dialog/bad.movie.genre.catagory.dialog
ovos_skill_moviemaster/locale/ca-es/dialog/bad.tv.genre.catagory.dialog
ovos_skill_moviemaster/locale/ca-es/dialog/fallback.api.dialog
ovos_skill_moviemaster/locale/ca-es/dialog/genre.movie.search.dialog
ovos_skill_moviemaster/locale/ca-es/dialog/genre.tv.search.dialog
ovos_skill_moviemaster/locale/ca-es/dialog/movie.cast.dialog
ovos_skill_moviemaster/locale/ca-es/dialog/movie.description.dialog
ovos_skill_moviemaster/locale/ca-es/dialog/movie.description.error.dialog
ovos_skill_moviemaster/locale/ca-es/dialog/movie.genre.multiple.dialog
ovos_skill_moviemaster/locale/ca-es/dialog/movie.genre.single.dialog
ovos_skill_moviemaster/locale/ca-es/dialog/movie.info.response.dialog
ovos_skill_moviemaster/locale/ca-es/dialog/movie.popular.dialog
ovos_skill_moviemaster/locale/ca-es/dialog/movie.production.multiple.dialog
ovos_skill_moviemaster/locale/ca-es/dialog/movie.production.single.dialog
ovos_skill_moviemaster/locale/ca-es/dialog/movie.recommendations.dialog
ovos_skill_moviemaster/locale/ca-es/dialog/movie.runtime.dialog
ovos_skill_moviemaster/locale/ca-es/dialog/movie.top.dialog
ovos_skill_moviemaster/locale/ca-es/dialog/movie.year.dialog
ovos_skill_moviemaster/locale/ca-es/dialog/movie.year.error.dialog
ovos_skill_moviemaster/locale/ca-es/dialog/no.api.dialog
ovos_skill_moviemaster/locale/ca-es/dialog/no.info.dialog
ovos_skill_moviemaster/locale/ca-es/dialog/no.info.general.dialog
ovos_skill_moviemaster/locale/ca-es/dialog/no.valid.api.dialog
ovos_skill_moviemaster/locale/da-dk/skill.json
ovos_skill_moviemaster/ovos_skill_moviemaster.egg-info/PKG-INFO
ovos_skill_moviemaster/ovos_skill_moviemaster.egg-info/SOURCES.txt
ovos_skill_moviemaster/ovos_skill_moviemaster.egg-info/dependency_links.txt
ovos_skill_moviemaster/ovos_skill_moviemaster.egg-info/entry_points.txt
ovos_skill_moviemaster/ovos_skill_moviemaster.egg-info/requires.txt
ovos_skill_moviemaster/ovos_skill_moviemaster.egg-info/top_level.txt
ovos_skill_moviemaster-0.0.12.dist-info/LICENSE
ovos_skill_moviemaster-0.0.12.dist-info/METADATA
ovos_skill_moviemaster-0.0.12.dist-info/WHEEL
ovos_skill_moviemaster-0.0.12.dist-info/entry_points.txt
ovos_skill_moviemaster-0.0.12.dist-info/top_level.txt
ovos_skill_moviemaster-0.0.12.dist-info/RECORD
