Metadata-Version: 2.1
Name: ovos-skill-moviemaster
Version: 0.0.12
Summary: OVOS hello world skill plugin
Home-page: https://github.com/OpenVoiceOS/ovos-skill-moviemaster
Author: OpenVoiceOS
Author-email: builderjer@gmail.com
License: Apache-2.0
Keywords: ovos skill plugin
License-File: LICENSE
Requires-Dist: tmdbv3api
Requires-Dist: ovos-utils<1.0.0,>=0.0.28
Requires-Dist: ovos-workshop<8.0.0,>=0.0.11
Requires-Dist: ovos-date-parser
Requires-Dist: ovos-number-parser
